gpar/__init__.py
gpar/model.py
gpar/regression.py
tests/__init__.py
tests/test_model.py
tests/test_regression.py
tests/util.py
gpar-0.3.2.dist-info/LICENCE.txt
gpar-0.3.2.dist-info/METADATA
gpar-0.3.2.dist-info/WHEEL
gpar-0.3.2.dist-info/top_level.txt
gpar-0.3.2.dist-info/RECORD
