Metadata-Version: 2.2
Name: gpar
Version: 0.3.2
Summary: Implementation of the Gaussian Process Autoregressive Regression Model
Home-page: https://github.com/wesselb/gpar
Author: Wessel Bruinsma
Author-email: wessel.p.bruinsma@gmail.com
License: MIT
Requires-Python: >=3.8
License-File: LICENCE.txt
Requires-Dist: numpy>=1.16
Requires-Dist: torch
Requires-Dist: wbml>=0.3
Requires-Dist: plum-dispatch>=2.5.7
Requires-Dist: backends>=1
Requires-Dist: backends-matrix>=1
Requires-Dist: stheno>=1.1
Requires-Dist: varz>=0.6
Dynamic: requires-dist
Dynamic: requires-python
